{
  "id":69,
  "title":"Avril 1935",
  "cat":{
    "id":3,
    "name":"Langlois, le b\u00e2tisseur"
  },
  "pos":8504,
  "desc":"<p>En avril 1935 a lieu le Congr\u00e8s international du film \u00e0 Berlin, r\u00e9unissant vingt pays europ\u00e9ens&nbsp;; on y recommande la cr\u00e9ation d'archives cin\u00e9matographiques dans tous les pays. En ao\u00fbt 1935, Langlois \u00e9crit un article dans <em>La Cin\u00e9matographie fran\u00e7aise<\/em> dans lequel il d\u00e9clare&nbsp;: <em>\u00ab&nbsp;La pr\u00e9servation du film suscite dans certains milieux un int\u00e9r\u00eat croissant. La cr\u00e9ation de cin\u00e9math\u00e8ques est probable&nbsp;\u00bb<\/em>. Un an plus tard, les projets se concr\u00e9tisent, et, en juin 1936, il \u00e9crit de nouveau dans l'hebdomadaire&nbsp;: <em>\u00ab&nbsp;Simultan\u00e9ment, dans le monde entier, on constitue des cin\u00e9math\u00e8ques actives. Ce mouvement a pour trait commun d'\u00eatre uniquement le fait d'initiatives priv\u00e9es suscit\u00e9es par l'enthousiasme. En g\u00e9n\u00e9ral, ce sont les jeunes g\u00e9n\u00e9rations qui s'int\u00e9ressent \u00e0 la survie des films, d\u00e9fendant le pass\u00e9 et travaillant de toutes leurs forces \u00e0 sauvegarder les chefs-d'\u0153uvres du cin\u00e9ma&nbsp;\u00bb<\/em>.<\/p>"
}